{"cameraMode":{"drawMode":0,"name":"Shaded","section":"Shading Mode"},"sceneLighting":false,"audioPlay":false,"sceneViewState":{"m_AlwaysRefresh":false,"showFog":true,"showSkybox":false,"showFlares":true,"showImageEffects":true,"showParticleSystems":true,"showVisualEffectGraphs":true,"m_FxEnabled":true},"in2DMode":false,"pivot":{"x":-0.469415545463562,"y":0.6430792808532715,"z":-7.188832759857178},"rotation":{"x":0.2660106420516968,"y":0.14452004432678224,"z":-0.04042854905128479,"w":0.9522663950920105},"size":1.8653234243392945,"orthographic":false}